hydromass/__init__.py
hydromass/constants.py
hydromass/contour.py
hydromass/delta.py
hydromass/deproject.py
hydromass/emissivity.py
hydromass/forward.py
hydromass/functions.py
hydromass/mhyd.py
hydromass/nonparametric.py
hydromass/plots.py
hydromass/pnt.py
hydromass/polytropic.py
hydromass/save.py
hydromass/tpdata.py
hydromass/wl.py
hydromass/data/coolfunc_table.fits
hydromass/data/pnt_covmat.dat
hydromass/data/pnt_mean.dat
hydromass-0.5.3.dist-info/METADATA
hydromass-0.5.3.dist-info/WHEEL
hydromass-0.5.3.dist-info/top_level.txt
hydromass-0.5.3.dist-info/RECORD
