Metadata-Version: 2.1
Name: hydromass
Version: 0.5.3
Summary: Hydrostatic mass calculator
Home-page: https://github.com/domeckert/hydromass
Author: Dominique Eckert, Vittorio Ghirardini, Stefano Ettori
Author-email: Dominique.Eckert@unige.ch
Requires-Dist: numpy
Requires-Dist: scipy
Requires-Dist: astropy
Requires-Dist: matplotlib
Requires-Dist: pymc
Requires-Dist: pytensor
Requires-Dist: pyproffit
Requires-Dist: numpyro
Requires-Dist: corner
